orthogonal/__init__.py
orthogonal/_version.py
orthogonal/doublyConnectedEdgeList/Dcel.py
orthogonal/doublyConnectedEdgeList/Face.py
orthogonal/doublyConnectedEdgeList/GraphElement.py
orthogonal/doublyConnectedEdgeList/Hedge.py
orthogonal/doublyConnectedEdgeList/Vertex.py
orthogonal/doublyConnectedEdgeList/__init__.py
orthogonal/mapping/EmbeddedTypes.py
orthogonal/mapping/EmbeddingToScreen.py
orthogonal/mapping/LayoutGrid.py
orthogonal/mapping/ScreenSize.py
orthogonal/mapping/__init__.py
orthogonal/mapping/exceptions/FailedPositioningException.py
orthogonal/mapping/exceptions/UnSupportedOperationException.py
orthogonal/mapping/exceptions/__init__.py
orthogonal/resources/__init__.py
orthogonal/resources/loggingConfiguration.json
orthogonal/topologyShapeMetric/Compaction.py
orthogonal/topologyShapeMetric/FlowNet.py
orthogonal/topologyShapeMetric/OrthogonalException.py
orthogonal/topologyShapeMetric/Orthogonalization.py
orthogonal/topologyShapeMetric/Planarization.py
orthogonal/topologyShapeMetric/TSM.py
orthogonal/topologyShapeMetric/__init__.py
orthogonal-1.3.1.dist-info/LICENSE
orthogonal-1.3.1.dist-info/METADATA
orthogonal-1.3.1.dist-info/WHEEL
orthogonal-1.3.1.dist-info/top_level.txt
orthogonal-1.3.1.dist-info/RECORD
