Metadata-Version: 2.1
Name: orthogonal
Version: 1.3.1
Summary: Orthogonal Graph Layout for Python 3
Author-email: "Humberto A. Sanchez II" <Humberto.A.Sanchez.II@gmail.com>
Maintainer-email: "Humberto A. Sanchez II" <Humberto.A.Sanchez.II@gmail.com>
License: GNU AFFERO GENERAL PUBLIC LICENSE
Project-URL: Repository, https://github.com/hasii2011/orthogonal
Keywords: pyut,graphics,layout
License-File: LICENSE
Requires-Dist: networkx>=3.4.2
